ct_snippets/__init__.py
ct_snippets/load_data.py
ct_snippets/load_sf_class.py
ct_snippets/sf_bulk.py
ct_snippets/variables.py
ct_snippets-0.1.dist-info/METADATA
ct_snippets-0.1.dist-info/WHEEL
ct_snippets-0.1.dist-info/top_level.txt
ct_snippets-0.1.dist-info/RECORD
