Metadata-Version: 2.1
Name: ct-snippets
Version: 0.1
Summary: Code to manage common College Track data processes
Home-page: https://github.com/college-track/ct_snippets
Author: Baker Renneckar
Author-email: brenneckar@collegetrack.org
License: MIT
Platform: UNKNOWN
Requires-Dist: pandas
Requires-Dist: simple-salesforce
Requires-Dist: reportforce
